sebureem/__init__.py
sebureem/admin.py
sebureem/app.py
sebureem/cli.py
sebureem/models.py
sebureem/setup_app.py
sebureem/views.py
sebureem/__pycache__/__init__.cpython-36.pyc
sebureem/__pycache__/admin.cpython-36.pyc
sebureem/__pycache__/app.cpython-36.pyc
sebureem/__pycache__/cli.cpython-36.pyc
sebureem/__pycache__/models.cpython-36.pyc
sebureem/__pycache__/setup_app.cpython-36.pyc
sebureem/__pycache__/views.cpython-36.pyc
sebureem/templates/sebureem.html
sebureem/templates/setup/admin.html
sebureem/templates/setup/config.html
sebureem/templates/setup/database.html
sebureem/templates/setup/index.html
sebureem/templates/setup/site.html
sebureem-0.2.1.dist-info/DESCRIPTION.rst
sebureem-0.2.1.dist-info/METADATA
sebureem-0.2.1.dist-info/RECORD
sebureem-0.2.1.dist-info/WHEEL
sebureem-0.2.1.dist-info/entry_points.txt
sebureem-0.2.1.dist-info/metadata.json
sebureem-0.2.1.dist-info/top_level.txt
