Metadata-Version: 2.0
Name: sebureem
Version: 0.2.1
Summary: A simple comment server
Home-page: https://framagit.org/Erwhann-Rouge/sebureem
Author: Guilhem "Erwhann-Rouge" MAS-PAITRAULT
Author-email: guilhem.mas-paitrault@protonmail.com
License: BSD-3-Clause/CECILL-B
Keywords: sebureem comments disqus
Platform: UNKNOWN
Classifier: Development Status :: 2 - Pre-Alpha
Classifier: Environment :: Web Environment
Classifier: Framework :: Flask
Classifier: License :: OSI Approved :: BSD License
Classifier: Programming Language :: Python :: 3
Classifier: Topic :: Internet :: WWW/HTTP :: WSGI :: Application
Requires-Dist: Flask (>=0.12)
Requires-Dist: bcrypt (>=3.1)
Requires-Dist: docopt (>=0.6)
Requires-Dist: peewee (>=2.10)
